dictparser/__init__.py
dictparser/_dictparser_data.py
dictparser/_engine.py
dictparser/_init_p311.py
dictparser/_init_p36.py
dictparser/_type_utils.py
dictparser/_type_utils_p310.py
dictparser/_type_utils_p36.py
dictparser/engine.py
dictparser/mapper.py
dictparser/pylint.py
dictparser/types.py
dictparser-0.1.10.dist-info/licenses/LICENSE
dictparser-0.1.10.dist-info/METADATA
dictparser-0.1.10.dist-info/WHEEL
dictparser-0.1.10.dist-info/top_level.txt
dictparser-0.1.10.dist-info/RECORD
