Metadata-Version: 2.4
Name: dictparser
Version: 0.1.10
Summary: A Class serialization/deserialization library
Project-URL: Homepage, https://github.com/tgoncalves87/dictparser
Project-URL: Issues, https://github.com/tgoncalves87/dictparser/issues
Classifier: Programming Language :: Python :: 3
Classifier: License :: OSI Approved :: MIT No Attribution License (MIT-0)
Classifier: Operating System :: OS Independent
Requires-Python: >=3.6
License-File: LICENSE
Requires-Dist: dataclasses; python_version < "3.7"
Requires-Dist: pyyaml
Dynamic: license-file
